// converted by version 1.3
// on Thu Aug 06 23:53:11 ICT 2020

.package test {
	.aid 0x11:0x11:0x22:0x22:0x11;
	.version 1.0;

	.imports {
		0xA0:0x0:0x0:0x0:0x62:0x1:0x1 1.3;		//javacard/framework
		0xA0:0x0:0x0:0x0:0x62:0x1:0x2 1.3;		//javacard/security
		0xA0:0x0:0x0:0x0:0x62:0x0:0x1 1.0;		//java/lang
	}

	.applet {
		0x11:0x11:0x22:0x22:0x11:0x0 test;
	}

	.constantPool {
		// 0
		instanceFieldRef 1.15 test/rsasig;
		// 1
		instanceFieldRef short test/sigLen;
		// 2
		instanceFieldRef 1.8 test/rsaPrivKey;
		// 3
		instanceFieldRef 1.9 test/rsaPublKey;
		// 4
		instanceFieldRef byte[] test/s1;
		// 5
		instanceFieldRef byte[] test/s2;
		// 6
		instanceFieldRef byte[] test/s3;
		// 7
		instanceFieldRef byte[] test/sig_buffer;
		// 8
		staticMethodRef 1.15.0(BZ)Ljavacard/security/Signature;;		// javacard/security/Signature.getInstance(BZ)Ljavacard/security/Signature;
			.descriptor	Ljavacard/security/Signature;	1.15;

		// 9
		classRef 1.16;		// javacard/security/KeyPair
		// 10
		staticMethodRef 1.16.0(BS)V;		// javacard/security/KeyPair.<init>(BS)V
		// 11
		virtualMethodRef 1.16.1()V;		// genKeyPair()V
		// 12
		virtualMethodRef 1.16.2()Ljavacard/security/PrivateKey;;		// getPrivate()Ljavacard/security/PrivateKey;
			.descriptor	Ljavacard/security/PrivateKey;	1.2;

		// 13
		virtualMethodRef 1.16.3()Ljavacard/security/PublicKey;;		// getPublic()Ljavacard/security/PublicKey;
			.descriptor	Ljavacard/security/PublicKey;	1.3;

		// 14
		staticMethodRef 1.13.0(BSZ)Ljavacard/security/Key;;		// javacard/security/KeyBuilder.buildKey(BSZ)Ljavacard/security/Key;
			.descriptor	Ljavacard/security/Key;	1.0;

		// 15
		classRef 1.8;		// javacard/security/RSAPrivateKey
		// 16
		staticMethodRef 0.3.0()V;		// javacard/framework/Applet.<init>()V
		// 17
		classRef 1.9;		// javacard/security/RSAPublicKey
		// 18
		classRef test;
		// 19
		staticMethodRef test/<init>()V;
		// 20
		virtualMethodRef 0.3.2([BSB)V;		// register([BSB)V
		// 21
		virtualMethodRef 0.3.3()Z;		// selectingApplet()Z
		// 22
		virtualMethodRef 0.10.1()[B;		// getBuffer()[B
		// 23
		virtualMethodRef 0.10.6()S;		// setIncomingAndReceive()S
		// 24
		staticMethodRef test/rsasig(Ljavacard/framework/APDU;)V;
			.descriptor	Ljavacard/framework/APDU;	0.10;

		// 25
		staticMethodRef test/rsaverify(Ljavacard/framework/APDU;)V;
			.descriptor	Ljavacard/framework/APDU;	0.10;

		// 26
		staticMethodRef 0.7.1(S)V;		// javacard/framework/ISOException.throwIt(S)V
		// 27
		virtualMethodRef 1.15.3(Ljavacard/security/Key;B)V;		// init(Ljavacard/security/Key;B)V
			.descriptor	Ljavacard/security/Key;	1.0;

		// 28
		virtualMethodRef 1.15.6([BSS)V;		// update([BSS)V
		// 29
		virtualMethodRef 1.15.5([BSS[BS)S;		// sign([BSS[BS)S
		// 30
		virtualMethodRef 0.10.7()S;		// setOutgoing()S
		// 31
		virtualMethodRef 0.10.9(S)V;		// setOutgoingLength(S)V
		// 32
		virtualMethodRef 0.10.5([BSS)V;		// sendBytesLong([BSS)V
		// 33
		virtualMethodRef 1.15.7([BSS[BSS)Z;		// verify([BSS[BSS)Z
		// 34
		virtualMethodRef 0.10.8(SS)V;		// setOutgoingAndSend(SS)V
	}

	.class public test 0 extends 0.3 {		// extends javacard/framework/Applet

		.fields {
			private 1.8 rsaPrivKey 0;		// Ljavacard/security/RSAPrivateKey;
			private 1.9 rsaPublKey 1;		// Ljavacard/security/RSAPublicKey;
			private 1.15 rsasig 2;		// Ljavacard/security/Signature;
			private byte[] s1 3;		// [B
			private byte[] s2 4;		// [B
			private byte[] s3 5;		// [B
			private byte[] sig_buffer 6;		// [B
			private short sigLen 7;		// S
			private static final byte INS_SIGN = 1;		// B
			private static final byte INS_VERIFY = 2;		// B
		}

		.publicMethodTable 7 {
			equals(Ljava/lang/Object;)Z;
			register()V;
			register([BSB)V;
			selectingApplet()Z;
			deselect()V;
			getShareableInterfaceObject(Ljavacard/framework/AID;B)Ljavacard/framework/Shareable;;
			select()Z;
			process(Ljavacard/framework/APDU;)V;
		}

		.packageMethodTable 0 {
		}

		.method private <init>()V {
			.stack 5;
			.locals 1;

				L0:	aload_0;
					invokespecial 16;		// javacard/framework/Applet.<init>()V
					aload_0;
					bspush 10;
					sconst_0;
					invokestatic 8;		// javacard/security/Signature.getInstance(BZ)Ljavacard/security/Signature;
					putfield_a 0;		// reference test/test.rsasig
					aload_0;
					sconst_5;
					bspush 8;
					getfield_s_this 1;		// short test/test.sigLen
					smul;
					sconst_0;
					invokestatic 14;		// javacard/security/KeyBuilder.buildKey(BSZ)Ljavacard/security/Key;
					checkcast 0 15;		// T_CLASSORINTERFACE javacard/security/RSAPrivateKey
					putfield_a 2;		// reference test/test.rsaPrivKey
					aload_0;
					sconst_4;
					bspush 8;
					getfield_s_this 1;		// short test/test.sigLen
					smul;
					sconst_0;
					invokestatic 14;		// javacard/security/KeyBuilder.buildKey(BSZ)Ljavacard/security/Key;
					checkcast 0 17;		// T_CLASSORINTERFACE javacard/security/RSAPublicKey
					putfield_a 3;		// reference test/test.rsaPublKey
					new 9;		// javacard/security/KeyPair
					dup;
					sconst_1;
					bspush 8;
					getfield_s_this 1;		// short test/test.sigLen
					smul;
					invokespecial 10;		// javacard/security/KeyPair.<init>(BS)V
					astore_1;
				L1:	aload_1;
					invokevirtual 11;		// genKeyPair()V
					aload_0;
					aload_1;
					invokevirtual 12;		// getPrivate()Ljavacard/security/PrivateKey;
					checkcast 0 15;		// T_CLASSORINTERFACE javacard/security/RSAPrivateKey
					putfield_a 2;		// reference test/test.rsaPrivKey
					aload_0;
					aload_1;
					invokevirtual 13;		// getPublic()Ljavacard/security/PublicKey;
					checkcast 0 17;		// T_CLASSORINTERFACE javacard/security/RSAPublicKey
					putfield_a 3;		// reference test/test.rsaPublKey
					aload_0;
					sconst_2;
					newarray 11;
					dup;
					sconst_0;
					sconst_1;
					bastore;
					dup;
					sconst_1;
					sconst_2;
					bastore;
					putfield_a 4;		// reference test/test.s1
					aload_0;
					sconst_3;
					newarray 11;
					dup;
					sconst_0;
					sconst_3;
					bastore;
					dup;
					sconst_1;
					sconst_4;
					bastore;
					dup;
					sconst_2;
					sconst_5;
					bastore;
					putfield_a 5;		// reference test/test.s2
					aload_0;
					sconst_2;
					newarray 11;
					dup;
					sconst_0;
					bspush 6;
					bastore;
					dup;
					sconst_1;
					bspush 7;
					bastore;
					putfield_a 6;		// reference test/test.s3
					aload_0;
					sspush 128;
					putfield_s 1;		// short test/test.sigLen
					aload_0;
					getfield_s_this 1;		// short test/test.sigLen
					newarray 11;
					putfield_a 7;		// reference test/test.sig_buffer
					return;
		}

		.method public static install([BSB)V 0 {
			.stack 5;
			.locals 0;

				L0:	new 18;		// test/test
					dup;
					invokespecial 19;		// test/test.<init>()V
					aload_0;
					sload_1;
					sconst_1;
					sadd;
					aload_0;
					sload_1;
					baload;
					invokevirtual 20;		// register([BSB)V
					return;
		}

		.method public process(Ljavacard/framework/APDU;)V 7 {
			.stack 2;
			.locals 1;

			.descriptor	Ljavacard/framework/APDU;	0.10;

				L0:	aload_0;
					invokevirtual 21;		// selectingApplet()Z
					ifeq L2;
				L1:	return;
				L2:	aload_1;
					invokevirtual 22;		// getBuffer()[B
					astore_2;
				L3:	aload_1;
					invokevirtual 23;		// setIncomingAndReceive()S
					pop;
					aload_2;
					sconst_1;
					baload;
					slookupswitch L6 2 1 L4 2 L5;
				L4:	aload_0;
					aload_1;
					invokespecial 24;		// test/test.rsasig(Ljavacard/framework/APDU;)V
					goto L7;
				L5:	aload_0;
					aload_1;
					invokespecial 25;		// test/test.rsaverify(Ljavacard/framework/APDU;)V
					goto L7;
				L6:	sspush 27904;
					invokestatic 26;		// javacard/framework/ISOException.throwIt(S)V
				L7:	return;
		}

		.method private rsasig(Ljavacard/framework/APDU;)V {
			.stack 6;
			.locals 0;

			.descriptor	Ljavacard/framework/APDU;	0.10;

				L0:	getfield_a_this 0;		// reference test/test.rsasig
					getfield_a_this 2;		// reference test/test.rsaPrivKey
					sconst_1;
					invokevirtual 27;		// init(Ljavacard/security/Key;B)V
					getfield_a_this 0;		// reference test/test.rsasig
					getfield_a_this 4;		// reference test/test.s1
					sconst_0;
					getfield_a_this 4;		// reference test/test.s1
					arraylength;
					invokevirtual 28;		// update([BSS)V
					getfield_a_this 0;		// reference test/test.rsasig
					getfield_a_this 5;		// reference test/test.s2
					sconst_0;
					getfield_a_this 5;		// reference test/test.s2
					arraylength;
					invokevirtual 28;		// update([BSS)V
					getfield_a_this 0;		// reference test/test.rsasig
					getfield_a_this 6;		// reference test/test.s3
					sconst_0;
					getfield_a_this 6;		// reference test/test.s3
					arraylength;
					getfield_a_this 7;		// reference test/test.sig_buffer
					sconst_0;
					invokevirtual 29;		// sign([BSS[BS)S
					pop;
					aload_1;
					invokevirtual 30;		// setOutgoing()S
					pop;
					aload_1;
					getfield_s_this 1;		// short test/test.sigLen
					invokevirtual 31;		// setOutgoingLength(S)V
					aload_1;
					getfield_a_this 7;		// reference test/test.sig_buffer
					sconst_0;
					getfield_s_this 1;		// short test/test.sigLen
					invokevirtual 32;		// sendBytesLong([BSS)V
					return;
		}

		.method private rsaverify(Ljavacard/framework/APDU;)V {
			.stack 7;
			.locals 2;

			.descriptor	Ljavacard/framework/APDU;	0.10;

				L0:	aload_1;
					invokevirtual 22;		// getBuffer()[B
					astore_2;
				L1:	getfield_a_this 0;		// reference test/test.rsasig
					getfield_a_this 3;		// reference test/test.rsaPublKey
					sconst_2;
					invokevirtual 27;		// init(Ljavacard/security/Key;B)V
					getfield_a_this 0;		// reference test/test.rsasig
					getfield_a_this 4;		// reference test/test.s1
					sconst_0;
					getfield_a_this 4;		// reference test/test.s1
					arraylength;
					invokevirtual 28;		// update([BSS)V
					getfield_a_this 0;		// reference test/test.rsasig
					getfield_a_this 5;		// reference test/test.s2
					sconst_0;
					getfield_a_this 5;		// reference test/test.s2
					arraylength;
					invokevirtual 28;		// update([BSS)V
					getfield_a_this 0;		// reference test/test.rsasig
					getfield_a_this 6;		// reference test/test.s3
					sconst_0;
					getfield_a_this 6;		// reference test/test.s3
					arraylength;
					getfield_a_this 7;		// reference test/test.sig_buffer
					sconst_0;
					getfield_s_this 1;		// short test/test.sigLen
					invokevirtual 33;		// verify([BSS[BSS)Z
					sstore_3;
				L2:	aload_2;
					sconst_0;
					sload_3;
					ifeq L4;
				L3:	sconst_1;
					goto L5;
				L4:	sconst_0;
				L5:	bastore;
					aload_1;
					sconst_0;
					sconst_1;
					invokevirtual 34;		// setOutgoingAndSend(SS)V
					return;
		}

	}

}
